defdict/DataFormat.py
defdict/DefDict.py
defdict/MapRule.py
defdict/SpaceDefinition.py
defdict/SpeedTest.py
defdict/StdConversion.py
defdict/StdDefinitions.py
defdict/StdUnit.py
defdict/Tmat.py
defdict/UnitType.py
defdict/__init__.py
defdict/_static_version.py
defdict/_version.py
defdict/system_keys.py
defdict-0.1.1.dist-info/METADATA
defdict-0.1.1.dist-info/WHEEL
defdict-0.1.1.dist-info/top_level.txt
defdict-0.1.1.dist-info/RECORD
