Metadata-Version: 2.4
Name: defdict
Version: 0.1.1
Summary: Defined Dictionary
Home-page: https://github.com/Suke0811/DefDict/
Author: UCLA LEMUR
License: LGPLv3
Project-URL: GitHub, https://github.com/Suke0811/DefDict
Classifier: Framework :: Robot Framework
Classifier: License :: OSI Approved :: GNU Lesser General Public License v3 (LGPLv3)
Classifier: Programming Language :: Python :: 3
Requires-Dist: numpy
Requires-Dist: scipy
Requires-Dist: unyt
Requires-Dist: pytest
Dynamic: author
Dynamic: classifier
Dynamic: home-page
Dynamic: license
Dynamic: project-url
Dynamic: requires-dist
Dynamic: summary
